pyheatdemand/__init__.py
pyheatdemand/_version_generated.py
pyheatdemand/processing.py
PyHeatDemand-0.1.3.dist-info/LICENSE
PyHeatDemand-0.1.3.dist-info/METADATA
PyHeatDemand-0.1.3.dist-info/WHEEL
PyHeatDemand-0.1.3.dist-info/top_level.txt
PyHeatDemand-0.1.3.dist-info/RECORD
