Metadata-Version: 2.1
Name: PyHeatDemand
Version: 0.1.3
Summary: Processing Tool for Heat Demand Data
Maintainer: Frank Strozyk, Eileen Herbst, Elias Humm né Khashfe
Maintainer-email: Alexander Jüstel <alexander.juestel@rwth-aachen.de>
License: GNU GENERAL PUBLIC LICENSE
Project-URL: Documentation, https://pyhd.readthedocs.io/en/latest/index.html
Project-URL: Home, https://pyhd.readthedocs.io/en/latest/index.html
Project-URL: Bug Tracker, https://github.com/AlexanderJuestel/pyheatdemand/issues
Project-URL: Repository, https://github.com/AlexanderJuestel/pyheatdemand
Project-URL: Source Code, https://github.com/AlexanderJuestel/pyheatdemand
Keywords: dataprocessing,geospatial,geographic-data,spatial-data,rasterdata,vectordata,geographic
Classifier: Development Status :: 5 - Production/Stable
Classifier: Intended Audience :: Science/Research
Classifier: Topic :: Scientific/Engineering :: Information Analysis
Classifier: Programming Language :: Python :: 3.8
Classifier: Programming Language :: Python :: 3.9
Classifier: Programming Language :: Python :: 3.10
Classifier: Programming Language :: Python :: 3.11
Classifier: License :: OSI Approved :: GNU General Public License v3 (GPLv3)
Classifier: Operating System :: OS Independent
Requires-Python: >=3.10
License-File: LICENSE
Requires-Dist: geopandas
Requires-Dist: rasterstats
Requires-Dist: matplotlib
Requires-Dist: tqdm
Requires-Dist: geopy
Requires-Dist: osmnx
Provides-Extra: build
Requires-Dist: setuptools ; extra == 'build'
Requires-Dist: wheel ; extra == 'build'
Requires-Dist: twine ; extra == 'build'
Requires-Dist: build ; extra == 'build'
Provides-Extra: optionals
Provides-Extra: test
Requires-Dist: pytest ; extra == 'test'
Requires-Dist: pytest-cov ; extra == 'test'
Requires-Dist: geopandas ; extra == 'test'
Requires-Dist: rasterstats ; extra == 'test'
Requires-Dist: matplotlib ; extra == 'test'
Requires-Dist: tqdm ; extra == 'test'
Requires-Dist: geopy ; extra == 'test'
Requires-Dist: osmnx ; extra == 'test'
Requires-Dist: black ; extra == 'test'
